{
  "deals": [
    {
      "brand": "Almo Nature",
      "cat_score": 3,
      "category": "wet_food",
      "confidence_score": 95,
      "created_at": "2026-07-06T08:05:33.226622+00:00",
      "id": 101,
      "post_title": "【闲置】国healthspan软骨素",
      "post_url": "https://m.douban.com/group/topic/493062961/",
      "price": 92.4,
      "product_name": "【闲置】国healthspan软骨素"
    },
    {
      "brand": "巅峰",
      "cat_score": 3,
      "category": "wet_food",
      "confidence_score": 95,
      "created_at": "2026-07-06T06:05:15.950571+00:00",
      "id": 100,
      "post_title": "【闲置】巅峰ziwi罐头鸡肉185g*10罐",
      "post_url": "https://m.douban.com/group/topic/493052865/",
      "price": 200.0,
      "product_name": "【闲置】巅峰ziwi罐头鸡肉185g*10罐"
    },
    {
      "brand": "NOW Fresh",
      "cat_score": 3,
      "category": "cat_food",
      "confidence_score": 85,
      "created_at": "2026-07-06T05:04:30.075464+00:00",
      "id": 99,
      "post_title": "【闲置】now3号胶囊洋车前子壳谷氨酰胺",
      "post_url": "https://m.douban.com/group/topic/491173837/",
      "price": 14.0,
      "product_name": "【闲置】now3号胶囊洋车前子壳谷氨酰胺"
    },
    {
      "brand": "爱肯拿",
      "cat_score": 4,
      "category": "cat_food",
      "confidence_score": 95,
      "created_at": "2026-07-06T02:54:31.663014+00:00",
      "id": 98,
      "post_title": "【闲置】不出了，求删",
      "post_url": "https://m.douban.com/group/topic/493036431/",
      "price": 270.0,
      "product_name": "【闲置】270出爱肯拿5.4kg，一共两袋，去年618囤的，26年11月..."
    },
    {
      "brand": "VE",
      "cat_score": 3,
      "category": "freeze_dried",
      "confidence_score": 90,
      "created_at": "2026-07-06T01:34:36.395018+00:00",
      "id": 97,
      "post_title": "【闲置】南昌送vetwish乳铁蛋白(仅限南昌自提，救助！)",
      "post_url": "https://m.douban.com/group/topic/491249965/",
      "price": 0.0,
      "product_name": "【闲置】南昌送vetwish乳铁蛋白(仅限南昌自提，救助！)"
    },
    {
      "brand": "Hill's Science Diet",
      "cat_score": 3,
      "category": "cat_food",
      "confidence_score": 95,
      "created_at": "2026-07-05T14:54:46.713870+00:00",
      "id": 96,
      "post_title": "【闲置】希尔斯zd猫粮 台版",
      "post_url": "https://m.douban.com/group/topic/484890856/",
      "price": 82.0,
      "product_name": "【闲置】希尔斯zd猫粮 台版"
    },
    {
      "brand": "Halo",
      "cat_score": 4,
      "category": "cat_food",
      "confidence_score": 95,
      "created_at": "2026-07-05T14:15:10.604769+00:00",
      "id": 95,
      "post_title": "【闲置】halo健美🐔5kg，250包邮非偏远",
      "post_url": "https://m.douban.com/group/topic/492996608/",
      "price": 250.0,
      "product_name": "【闲置】halo健美🐔5kg，250包邮非偏远"
    },
    {
      "brand": "爱肯拿",
      "cat_score": 5,
      "category": "cat_food",
      "confidence_score": 95,
      "created_at": "2026-07-05T14:15:10.593392+00:00",
      "id": 94,
      "post_title": "闲置，爱肯拿2.8kg+，120包邮",
      "post_url": "https://m.douban.com/group/topic/492996810/",
      "price": 120.0,
      "product_name": "闲置，爱肯拿2.8kg+，120包邮"
    },
    {
      "brand": "百利",
      "cat_score": 5,
      "category": "cat_food",
      "confidence_score": 95,
      "created_at": "2026-07-05T12:54:28.489743+00:00",
      "id": 93,
      "post_title": "【闲置】百利无谷鸡5kg",
      "post_url": "https://m.douban.com/group/topic/492987341/",
      "price": 260.0,
      "product_name": "【闲置】百利无谷鸡5kg"
    },
    {
      "brand": "Royal Canin",
      "cat_score": 3,
      "category": "cat_food",
      "confidence_score": 95,
      "created_at": "2026-07-05T12:14:44.599515+00:00",
      "id": 92,
      "post_title": "【闲置】皇家肠道处方粮2kg",
      "post_url": "https://m.douban.com/group/topic/492982091/",
      "price": 180.0,
      "product_name": "【闲置】皇家肠道处方粮2kg"
    },
    {
      "brand": "VE",
      "cat_score": 3,
      "category": "freeze_dried",
      "confidence_score": 90,
      "created_at": "2026-07-05T11:44:07.644907+00:00",
      "id": 91,
      "post_title": "闲置 ve猪肉粒",
      "post_url": "https://m.douban.com/group/topic/492113028/",
      "price": 0.0,
      "product_name": "闲置 ve猪肉粒"
    },
    {
      "brand": "百利",
      "cat_score": 5,
      "category": "cat_food",
      "confidence_score": 95,
      "created_at": "2026-07-05T11:34:38.375538+00:00",
      "id": 90,
      "post_title": "删",
      "post_url": "https://m.douban.com/group/topic/492975532/",
      "price": 250.0,
      "product_name": "闲置猫粮｜百利无谷鸡肉250 约4.7kg"
    },
    {
      "brand": "Royal Canin",
      "cat_score": 3,
      "category": "cat_food",
      "confidence_score": 95,
      "created_at": "2026-07-05T09:54:16.266294+00:00",
      "id": 89,
      "post_title": "【闲置】佳乐滋消臭珠10元包邮",
      "post_url": "https://m.douban.com/group/topic/492964499/",
      "price": 3.0,
      "product_name": "【闲置】地狱厨房咕噜酱，皇家奶罐（临期），佳乐滋消臭珠"
    },
    {
      "brand": "渴望",
      "cat_score": 4,
      "category": "cat_food",
      "confidence_score": 95,
      "created_at": "2026-07-05T04:34:13.017246+00:00",
      "id": 88,
      "post_title": "【闲置】渴望室内伴侣",
      "post_url": "https://m.douban.com/group/topic/492935952/",
      "price": 325.0,
      "product_name": "【闲置】渴望室内伴侣"
    },
    {
      "brand": "渴望",
      "cat_score": 5,
      "category": "cat_food",
      "confidence_score": 95,
      "created_at": "2026-07-05T03:04:04.971633+00:00",
      "id": 87,
      "post_title": "闲置渴望六种鱼",
      "post_url": "https://m.douban.com/group/topic/492929427/",
      "price": 350.0,
      "product_name": "闲置渴望六种鱼"
    },
    {
      "brand": "爱肯拿",
      "cat_score": 4,
      "category": "cat_food",
      "confidence_score": 90,
      "created_at": "2026-07-05T02:43:54.501441+00:00",
      "id": 86,
      "post_title": "闲置6.18猫粮买多了有渴望爱肯拿",
      "post_url": "https://m.douban.com/group/topic/492927638/",
      "price": 0.0,
      "product_name": "闲置6.18猫粮买多了有渴望爱肯拿"
    },
    {
      "brand": "MJamJam",
      "cat_score": 4,
      "category": "wet_food",
      "confidence_score": 90,
      "created_at": "2026-07-05T02:33:38.728110+00:00",
      "id": 85,
      "post_title": "【闲置】出满满鲱鱼螃蟹鸡和mj袋鼠餐包",
      "post_url": "https://m.douban.com/group/topic/492927379/",
      "price": 0.0,
      "product_name": "【闲置】出满满鲱鱼螃蟹鸡和mj袋鼠餐包"
    },
    {
      "brand": "法米娜",
      "cat_score": 5,
      "category": "cat_food",
      "confidence_score": 95,
      "created_at": "2026-07-05T01:29:34.363541+00:00",
      "id": 84,
      "post_title": "280r出闲置官旗全新未拆法米娜石榴鸡",
      "post_url": "https://m.douban.com/group/topic/492923381/",
      "price": 280.0,
      "product_name": "280r出闲置官旗全新未拆法米娜石榴鸡"
    },
    {
      "brand": "Halo",
      "cat_score": 5,
      "category": "cat_food",
      "confidence_score": 95,
      "created_at": "2026-07-04T19:03:28.925634+00:00",
      "id": 83,
      "post_title": "【闲置】halo自然光环2.5kg未拆封",
      "post_url": "https://m.douban.com/group/topic/492093629/",
      "price": 190.0,
      "product_name": "【闲置】halo自然光环2.5kg未拆封"
    },
    {
      "brand": "法米娜",
      "cat_score": 4,
      "category": "cat_food",
      "confidence_score": 95,
      "created_at": "2026-07-04T18:13:47.913905+00:00",
      "id": 82,
      "post_title": "【闲置】法米娜南瓜鸭",
      "post_url": "https://m.douban.com/group/topic/491918346/",
      "price": 230.0,
      "product_name": "【闲置】法米娜南瓜鸭"
    }
  ],
  "latest_run": {
    "deals_created": 0,
    "finished_at": "2026-07-06T10:54:47.070972+00:00",
    "notifications_sent": 0,
    "posts_seen": 53
  },
  "published_at": "2026-07-06T10:54:47.182944+00:00"
}
